{
  "last_updated": "2026-06-23 23:25",
  "headlines": [
    {
      "category": "Crime",
      "title": "Two men linked to Cambodia-based scam syndicate Prince Group investigated for money laundering offences",
      "source": "CNA",
      "url": "https://www.channelnewsasia.com/singapore/cambodia-scam-prince-holding-group-foreigners-arrested-money-laundering-6204136",
      "published": "2026-06-23 23:17"
    },
    {
      "category": "Crime",
      "title": "Two teens to be charged over roadblock evasion, crash that injured police and LTA officers",
      "source": "CNA",
      "url": "https://www.channelnewsasia.com/singapore/teenager-evade-roadblock-injure-police-lta-officers-6203831",
      "published": "2026-06-23 21:32"
    },
    {
      "category": "Crime",
      "title": "S'pore PR, 33, slaps church attendees after he was stopped from taking free bible, gets 5 weeks' jail",
      "source": "Mothership",
      "url": "https://mothership.sg/2026/06/man-slaps-church-attendees-no-free-bible/",
      "published": "2026-06-23 22:38"
    },
    {
      "category": "Crime",
      "title": "S’pore teacher, 45, repeatedly used pen to jab head of young boy with special needs, gets 18 months’ jail",
      "source": "Mothership",
      "url": "https://mothership.sg/2026/06/teacher-jabs-special-needs-boy-pen/",
      "published": "2026-06-23 19:52"
    },
    {
      "category": "Crime",
      "title": "Man, 35, molested SIA stewardess during flight while friends laughed",
      "source": "Mothership",
      "url": "https://mothership.sg/2026/06/man-molested-sia-stewardess-friends-laughed/",
      "published": "2026-06-23 19:40"
    },
    {
      "category": "Crime",
      "title": "S'porean man, 59, who exposed himself to female officer after alleged molest in Sembawang jailed 12 weeks",
      "source": "Mothership",
      "url": "https://mothership.sg/2026/06/molestation-expose-female-police-officer/",
      "published": "2026-06-23 19:39"
    },
    {
      "category": "Crime",
      "title": "Man arrested for allegedly stealing $50,000 during meeting to purchase cryptocurrency",
      "source": "Straits Times",
      "url": "https://www.straitstimes.com/singapore/man-arrested-for-allegedly-stealing-50000-during-meeting-to-purchase-cryptocurrency",
      "published": "2026-06-23 23:10"
    },
    {
      "category": "Crime",
      "title": "2 teens to be charged over separate cases of roadblock evasion, seriously injuring officers on duty",
      "source": "Straits Times",
      "url": "https://www.straitstimes.com/singapore/2-teens-to-be-charged-over-separate-cases-of-roadblock-evasion-seriously-injuring-officers-on-duty",
      "published": "2026-06-23 21:16"
    },
    {
      "category": "Crime",
      "title": "Genting Dream, Star Voyager guests departing from S’pore will have fuel charge waived",
      "source": "Straits Times",
      "url": "https://www.straitstimes.com/singapore/genting-dream-star-voyager-passengers-no-longer-have-to-pay-fuel-surcharges-from-june-26",
      "published": "2026-06-23 20:01"
    },
    {
      "category": "Crime",
      "title": "Ex-SAF captain admits to cheating victims of over $143k, dealing with vape devices in camp",
      "source": "Straits Times",
      "url": "https://www.straitstimes.com/singapore/courts-crime/ex-saf-captain-admits-to-cheating-victims-of-over-143k-dealing-with-vape-devices-in-camp",
      "published": "2026-06-23 19:05"
    },
    {
      "category": "Crime",
      "title": "Hit-and-run on CTE: Van driver who drove against traffic arrested",
      "source": "Straits Times",
      "url": "https://www.straitstimes.com/singapore/hit-and-run-on-cte-van-driver-who-drove-against-traffic-arrested",
      "published": "2026-06-23 16:40"
    },
    {
      "category": "Crime",
      "title": "LTA impersonation phishing scams on the rise again, with at least $74,000 lost in 3 weeks",
      "source": "Straits Times",
      "url": "https://www.straitstimes.com/singapore/lta-impersonation-phishing-scams-on-the-rise-again-with-at-least-74000-lost-in-3-weeks",
      "published": "2026-06-22 20:53"
    },
    {
      "category": "Crime",
      "title": "Ex-childcare teacher gets 1½ years’ jail for using pen to stab special needs boy’s head repeatedly",
      "source": "Straits Times",
      "url": "https://www.straitstimes.com/singapore/courts-crime/ex-childcare-teacher-gets-11-2-years-jail-for-using-pen-to-stab-special-needs-boys-head-repeatedly",
      "published": "2026-06-22 18:34"
    },
    {
      "category": "Crime",
      "title": "S’pore High Court halts defamation suit filed by X Corp, says case should be heard in US",
      "source": "Straits Times",
      "url": "https://www.straitstimes.com/singapore/courts-crime/spore-high-court-halts-defamation-suit-filed-by-x-corp-says-case-should-be-heard-in-us",
      "published": "2026-06-22 17:40"
    },
    {
      "category": "Crime",
      "title": "Jail for man who exposed himself to police officer after his arrest for molestation",
      "source": "Straits Times",
      "url": "https://www.straitstimes.com/singapore/courts-crime/jail-for-man-who-exposed-himself-to-police-officer-after-his-arrest-for-molestation",
      "published": "2026-06-22 17:37"
    },
    {
      "category": "Crime",
      "title": "Jail for man who molested SIA stewardess and harassed her during a flight",
      "source": "Straits Times",
      "url": "https://www.straitstimes.com/singapore/courts-crime/jail-for-man-who-molested-sia-stewardess-and-harassed-her-during-a-flight",
      "published": "2026-06-22 17:34"
    },
    {
      "category": "Crime",
      "title": "Man helped Cambodian crime ring collect over $656k from Singapore victims of scam calls",
      "source": "Straits Times",
      "url": "https://www.straitstimes.com/singapore/courts-crime/man-helped-cambodia-crime-group-collect-over-656k-from-singapore-victims-of-scam-calls",
      "published": "2026-06-22 15:50"
    },
    {
      "category": "Crime",
      "title": "11 months’ jail for man who downloaded child abuse material",
      "source": "Straits Times",
      "url": "https://www.straitstimes.com/singapore/courts-crime/11-months-jail-for-man-who-downloaded-child-abuse-material",
      "published": "2026-06-22 15:34"
    },
    {
      "category": "Crime",
      "title": "Police looking for hit-and-run van driver who also drove against traffic on CTE",
      "source": "Straits Times",
      "url": "https://www.straitstimes.com/singapore/police-looking-for-hit-and-run-van-driver-who-also-drove-against-traffic-on-cte",
      "published": "2026-06-22 13:20"
    },
    {
      "category": "Traffic",
      "title": "Iran says card-based banking hit by cyberattack on three lenders",
      "source": "CNA",
      "url": "https://www.channelnewsasia.com/business/iran-says-card-based-banking-hit-cyberattack-three-lenders-6203756",
      "published": "2026-06-23 20:35"
    },
    {
      "category": "Traffic",
      "title": "Chinese man, 75, raises daughter, 6, while caring for ill wife, says he wants to ‘live a few more decades’",
      "source": "Mothership",
      "url": "https://mothership.sg/2026/06/chinese-man-75-raise-kid/",
      "published": "2026-06-23 21:42"
    },
    {
      "category": "Traffic",
      "title": "S'pore impounds 7 vehicles suspected of offering illegal cross-border ride-hailing services",
      "source": "Mothership",
      "url": "https://mothership.sg/2026/06/singapore-impounds-vehicles-cross-border/",
      "published": "2026-06-23 21:20"
    },
    {
      "category": "Traffic",
      "title": "ITE students build online education and career guide they wish had existed for them",
      "source": "Straits Times",
      "url": "https://www.straitstimes.com/singapore/parenting-education/whats-next-ite-students-build-online-education-and-career-guide-they-wish-had-existed-for-them",
      "published": "2026-06-23 18:55"
    },
    {
      "category": "Traffic",
      "title": "Singapore-bound SIA flight delayed 6 hours in Kuala Lumpur due to deflated tyres, bad weather",
      "source": "Straits Times",
      "url": "https://www.straitstimes.com/singapore/singapore-bound-sia-flight-delayed-6-hours-in-kuala-lumpur-due-to-deflated-tyres",
      "published": "2026-06-22 16:35"
    },
    {
      "category": "Traffic",
      "title": "7 stalls in Chinatown Complex Food Centre affected by exhaust fan outage",
      "source": "Straits Times",
      "url": "https://www.straitstimes.com/singapore/7-stalls-in-chinatown-complex-food-centre-affected-by-exhaust-fan-outage",
      "published": "2026-06-22 13:59"
    },
    {
      "category": "Traffic",
      "title": "Mandatory treatment order report called for man responsible for Joo Seng Road fire",
      "source": "Straits Times",
      "url": "https://www.straitstimes.com/singapore/courts-crime/mandatory-treatment-order-report-called-for-man-responsible-for-joo-seng-road-fire",
      "published": "2026-06-22 13:55"
    },
    {
      "category": "Traffic",
      "title": "Five evacuated after fire involving charging e-bike left unattended in Geylang condo",
      "source": "Straits Times",
      "url": "https://www.straitstimes.com/singapore/five-evacuated-after-fire-involving-charging-pab-left-unattended-in-geylang-condo",
      "published": "2026-06-22 08:25"
    },
    {
      "category": "Money",
      "title": "Man in Punggol gets S$10 FairPrice voucher from neighbour as apology for renovation noise",
      "source": "Mothership",
      "url": "https://mothership.sg/2026/06/neighbours-give-voucher-renovation-noise/",
      "published": "2026-06-24 00:02"
    },
    {
      "category": "Money",
      "title": "Petrol, diesel prices ease in Singapore as oil prices fall",
      "source": "Straits Times",
      "url": "https://www.straitstimes.com/singapore/transport/petrol-diesel-prices-ease-in-singapore-as-oil-prices-slip",
      "published": "2026-06-23 17:30"
    },
    {
      "category": "Money",
      "title": "Durian prices in Singapore drop, but sellers say unlikely to match Malaysia’s lows",
      "source": "Straits Times",
      "url": "https://www.straitstimes.com/singapore/durian-prices-in-singapore-drop-sellers-say-unlikely-to-match-malaysias-lows",
      "published": "2026-06-23 17:22"
    },
    {
      "category": "General",
      "title": "Senegal skipper Koulibaly owns up to mistakes against Norway",
      "source": "CNA",
      "url": "https://www.channelnewsasia.com/sport/senegal-skipper-koulibaly-owns-up-mistakes-against-norway-6204186",
      "published": "2026-06-23 23:15"
    },
    {
      "category": "General",
      "title": "Netherlands gun for top spot against hapless Tunisia",
      "source": "CNA",
      "url": "https://www.channelnewsasia.com/sport/netherlands-gun-top-spot-against-hapless-tunisia-6204191",
      "published": "2026-06-23 23:14"
    },
    {
      "category": "General",
      "title": "Belgium's Doku set to rejoin World Cup squad after son's birth",
      "source": "CNA",
      "url": "https://www.channelnewsasia.com/sport/belgiums-doku-set-rejoin-world-cup-squad-after-sons-birth-6204111",
      "published": "2026-06-23 22:46"
    },
    {
      "category": "General",
      "title": "Red Roses secure hefty raise, World Cup bonus in new four-year pay deal",
      "source": "CNA",
      "url": "https://www.channelnewsasia.com/sport/red-roses-secure-hefty-raise-world-cup-bonus-in-new-four-year-pay-deal-6204071",
      "published": "2026-06-23 22:29"
    },
    {
      "category": "General",
      "title": "India's Bajaj Auto says ransomware attack hits systems",
      "source": "CNA",
      "url": "https://www.channelnewsasia.com/business/indias-bajaj-auto-says-ransomware-attack-hits-systems-6204031",
      "published": "2026-06-23 22:09"
    },
    {
      "category": "General",
      "title": "US agencies have seized more than 300 drones near World Cup sites, TSA says",
      "source": "CNA",
      "url": "https://www.channelnewsasia.com/sport/us-agencies-have-seized-more-300-drones-near-world-cup-sites-tsa-says-6204001",
      "published": "2026-06-23 21:55"
    },
    {
      "category": "General",
      "title": "PGA Tour announces two-tier competitive model from 2028",
      "source": "CNA",
      "url": "https://www.channelnewsasia.com/sport/pga-tour-announces-two-tier-competitive-model-2028-6203961",
      "published": "2026-06-23 21:39"
    },
    {
      "category": "General",
      "title": "Serena's return puts familiar force at centre of Wimbledon",
      "source": "CNA",
      "url": "https://www.channelnewsasia.com/sport/serenas-return-puts-familiar-force-centre-wimbledon-6203896",
      "published": "2026-06-23 21:17"
    },
    {
      "category": "General",
      "title": "Former Italy coach Gattuso joins Lazio as manager",
      "source": "CNA",
      "url": "https://www.channelnewsasia.com/sport/former-italy-coach-gattuso-joins-lazio-manager-6203881",
      "published": "2026-06-23 21:10"
    },
    {
      "category": "General",
      "title": "Meta launches cheaper range of AI smart glasses starting at $299",
      "source": "CNA",
      "url": "https://www.channelnewsasia.com/business/meta-launches-cheaper-range-ai-smart-glasses-starting-299-6203876",
      "published": "2026-06-23 21:09"
    }
  ]
}