{
  "source_name": "Singapore Pools",
  "source_url": "https://www.singaporepools.com.sg/en/product/pages/4d_results.aspx",
  "last_updated": "2026-07-01T21:49:24.934458+00:00",
  "four_d": {
    "source_url": "https://www.singaporepools.com.sg/en/product/pages/4d_results.aspx",
    "data_url": "https://www.singaporepools.com.sg/DataFileArchive/Lottery/Output/fourd_result_top_draws_en.html",
    "draw_date": "Wed, 01 Jul 2026",
    "draw_no": "5503",
    "first_prize": "6428",
    "second_prize": "6234",
    "third_prize": "9596",
    "starter": [
      "0927",
      "4561",
      "5664",
      "6543",
      "7638",
      "7680",
      "7902",
      "8886",
      "9796",
      "9818"
    ],
    "consolation": [
      "0707",
      "1242",
      "1722",
      "2534",
      "3674",
      "4828",
      "7927",
      "8506",
      "9180",
      "9386"
    ]
  },
  "toto": {
    "source_url": "https://www.singaporepools.com.sg/en/product/pages/toto_results.aspx",
    "data_url": "https://www.singaporepools.com.sg/DataFileArchive/Lottery/Output/toto_result_top_draws_en.html",
    "draw_date": "Mon, 29 Jun 2026",
    "draw_no": "4195",
    "winning_numbers": [
      "29",
      "6",
      "11",
      "22",
      "23",
      "31"
    ],
    "additional_number": "34"
  }
}